dbml_to_fides/__init__.py
dbml_to_fides/cli.py
dbml_to_fides/transform.py
dbml_to_fides-1.0.0a6.dist-info/LICENSE.txt
dbml_to_fides-1.0.0a6.dist-info/METADATA
dbml_to_fides-1.0.0a6.dist-info/WHEEL
dbml_to_fides-1.0.0a6.dist-info/entry_points.txt
dbml_to_fides-1.0.0a6.dist-info/top_level.txt
dbml_to_fides-1.0.0a6.dist-info/RECORD
