Metadata-Version: 2.1
Name: dbml-to-fides
Version: 1.0.0a6
Summary: Interoperatbility for DBML and Fides dataset manifests
Author-email: Ee Durbin <ee.opensource@pyfound.org>
License: Copyright 2023 Ee Durbin
Project-URL: Homepage, https://github.com/ewdurbin/dbml-to-fides
Project-URL: Source, https://github.com/ewdurbin/dbml-to-fides
Keywords: fides,dbml
Classifier: Development Status :: 3 - Alpha
Classifier: Intended Audience :: Developers
Classifier: Topic :: Software Development :: Build Tools
Classifier: License :: OSI Approved :: MIT License
Classifier: Programming Language :: Python :: 3
Classifier: Programming Language :: Python :: 3.8
Classifier: Programming Language :: Python :: 3.9
Classifier: Programming Language :: Python :: 3.10
Classifier: Programming Language :: Python :: 3.11
Classifier: Programming Language :: Python :: 3 :: Only
Requires-Python: <4,>=3.8
License-File: LICENSE.txt
Requires-Dist: click
Requires-Dist: deepmerge
Requires-Dist: fideslang
Requires-Dist: pydbml
Requires-Dist: pyaml
Requires-Dist: typing-extensions (<4.6.0)
